[
  {"id":"memo.identity-assigned","from":"Oddělení Přidělené Identity","subject":"Identita byla přiřazena","priority":"system","delivery":"modal-once","trigger":{"kind":"flagSet","flag":"identity.assigned"},"body":["Vaše pracovní identita byla vytvořena lokálně. Jméno nebylo vyžadováno.","Pokračujte vstupním auditem. Přítomnost bude považována za platnou po jejím řádném zaznamenání."]},
  {"id":"memo.audit-00-a-complete","from":"Centrum Provozní Přítomnosti","subject":"Vstupní audit přijat","priority":"normal","delivery":"inbox","trigger":{"kind":"formSubmitted","formId":"audit-00-a"},"body":["Formulář 00-A byl přijat bez zjevného rozporu se svou vlastní existencí.","Během vyplňování bylo zaznamenáno několik kliků. Tyto kliky byly zpětně uznány jako první pracovní výstup."]},
  {"id":"memo.audit-trace-available","from":"Oddělení Auditního Pohybu","subject":"Možnost rozšířit auditní stopu","priority":"normal","delivery":"inbox","trigger":{"kind":"formSubmitted","formId":"audit-10-a"},"body":["Dosavadní objem evidence umožňuje zavedení další evidence.","Standardizace auditních dávek je nyní připravena k nákupu v provozním účtu."]},
  {"id":"memo.audit-trace-approved","from":"Oddělení Auditního Pohybu","subject":"Rozšíření auditní stopy schváleno","priority":"normal","delivery":"toast-and-inbox","trigger":{"kind":"upgradeOwned","upgradeId":"sys.audit-batch-standardization"},"body":["Každých 25 interakcí lze od této chvíle spojit do jednoho auditního balíčku.","Počet kliků se nezměnil. Jejich administrativní hustota ano."]},
  {"id":"memo.manual-evidence-saturation","from":"Analytika Nezpochybnitelného Objeme","subject":"Evidence se blíží nasycení","priority":"low","delivery":"inbox","trigger":{"kind":"eventCountAtLeast","eventType":"clickaudit.click","count":200},"body":["Další jednotlivé kliky budou mít nižší výkazní hodnotu.","Kliky jsou nadále vítány. Systém pouze přestal předstírat, že každý nový klik je stejně překvapivý."]},
  {"id":"memo.clickaudit-certified","from":"Komise pro Důkaz Přítomnosti","subject":"Certifikace přítomnostního auditu","priority":"high","delivery":"modal-once","trigger":{"kind":"moduleCertified","moduleId":"click-audit"},"body":["Oddělení potvrzuje, že jste opakováním důkazu dostatečně prokázali schopnost dokazovat.","Certifikace zůstane platná i po uzavření auditního cyklu, dokud nebude zpochybněna budoucí revizí."]},
  {"id":"memo.fidget-requisition","from":"Oddělení Taktilní Stabilizace","subject":"Autorizace stabilizačního vybavení","priority":"normal","delivery":"inbox","trigger":{"kind":"formSubmitted","formId":"audit-16-c"},"body":["Jedna Evidence byla přidělena žádosti.","Modulu Fidget bylo uděleno povolení k nasazení.","Samotné nasazení je vedeno jako samostatná činnost."]},
  {"id":"memo.first-settle","from":"Oddělení Taktilní Stabilizace","subject":"První přirozený doběh","priority":"low","delivery":"toast-and-inbox","trigger":{"kind":"eventCountAtLeast","eventType":"fidget.sessionSettled","count":1},"body":["Pohyb byl zahájen, stabilizován a ponechán k přirozenému zastavení.","Zastavení bylo uznáno jako výsledek. Řešení nebylo vyžadováno."]},
  {"id":"memo.fidget-certified","from":"Komise pro Stabilizaci Rozptýlením","subject":"Certifikace přirozeného doběhu","priority":"high","delivery":"modal-once","trigger":{"kind":"moduleCertified","moduleId":"fidget"},"body":["Byla potvrzena schopnost dokončit celý rotační cyklus bez přerušení jeho koncem.","Stabilizace může být od nynějška uváděna jako získaná kompetence."]},
  {"id":"memo.entropy-elevated","from":"Procesní Klima","subject":"Entropy překročila doporučenou neurčitost","priority":"warning","delivery":"toast-and-inbox","trigger":{"kind":"resourceAtLeast","resourceId":"entropy","amount":70},"body":["Systém zaznamenal zvýšený výskyt drobných nesouladů.","Doporučuje se stabilizační modul, zahrádka nebo vědomé ignorování stavu do další revize."]},
  {"id":"memo.bloom-access","from":"Care & Growth Enablement","subject":"Compliance zahrádka otevřena","priority":"normal","delivery":"inbox","trigger":{"kind":"formSubmitted","formId":"audit-23-b"},"body":["Drobným stavům byl přidělen bezpečný povrch pro růst.","Červené kameny nejsou chyba. Jsou výsledek, který vyžaduje jiný typ péče."]},
  {"id":"memo.bloom-first-wave","from":"Care & Growth Enablement","subject":"První vlna zpracována","priority":"low","delivery":"toast-and-inbox","trigger":{"kind":"eventCountAtLeast","eventType":"bloom.waveAdvanced","count":1},"body":["První vlna byla uzavřena a nahrazena další vlnou.","Tento postup byl vyhodnocen jako růst."]},
  {"id":"memo.red-stone-observed","from":"Oddělení Stavových Výjimek","subject":"Červený stav nebyl označen jako chyba","priority":"warning","delivery":"inbox","trigger":{"kind":"eventCountAtLeast","eventType":"bloom.redStoneSpawned","count":1},"body":["Na zahrádce byl zaznamenán červený kámen.","Nevyvozujte závěry z barvy. Závěry budou přiděleny oddělením, které vznikne později."]},
  {"id":"memo.bloom-certified","from":"Komise pro Procedurální Růst","subject":"Certifikace osmivlnného růstu","priority":"high","delivery":"modal-once","trigger":{"kind":"moduleCertified","moduleId":"bloom"},"body":["Růst byl zopakován dostatečně často, aby přestal působit náhodně.","Compliance zahrádka je certifikována pro další cykly."]},
  {"id":"memo.corner-waiver","from":"Oddělení Rohového Očekávání","subject":"Pasivní pozorování schváleno","priority":"normal","delivery":"inbox","trigger":{"kind":"formSubmitted","formId":"audit-27-r"},"body":["Čekání na roh bylo uznáno jako činnost s neurčeným termínem dokončení.","Zásah rohu bude zaznamenán i tehdy, pokud se v rozhodující chvíli díváte jinam."]},
  {"id":"memo.corner-near-miss","from":"Oddělení Rohového Očekávání","subject":"Téměř významné","priority":"low","delivery":"toast-and-inbox","trigger":{"kind":"eventCountAtLeast","eventType":"corner.nearMiss","count":1},"body":["Logo roh minulo způsobem, který lze při správné prezentaci považovat za pokrok.","Událost byla zařazena do Patience Units."]},
  {"id":"memo.corner-hit","from":"Oddělení Rohového Očekávání","subject":"Roh byl dosažen","priority":"ceremonial","delivery":"modal-once","trigger":{"kind":"eventCountAtLeast","eventType":"corner.cornerHit","count":1},"body":["Roh byl dosažen v souladu s geometrickými možnostmi obrazovky.","Význam události nebyl navýšen. Pouze její slavnostní zpracování."]},
  {"id":"memo.button-access","from":"Oddělení Opakovaného Souhlasu","subject":"Potvrzovací panel připojen","priority":"normal","delivery":"inbox","trigger":{"kind":"formSubmitted","formId":"audit-31-f"},"body":["Na pracovní stanici byl připojen panel, který umožňuje potvrzovat připravenost k potvrzení.","Kontrolky mohou signalizovat stav. Stav nemusí signalizovat význam."]},
  {"id":"memo.first-confirmation","from":"Oddělení Opakovaného Souhlasu","subject":"První sekvence potvrzena","priority":"low","delivery":"toast-and-inbox","trigger":{"kind":"eventCountAtLeast","eventType":"button.sequenceCompleted","count":1},"body":["Sekvence byla provedena ve správném pořadí, které bylo vytvořeno po jejím provedení.","Approval Units byly připsány."]},
  {"id":"memo.false-positive-review","from":"Quality of Confirmation","subject":"Správný stisk vyhodnocen jako procesně podezřelý","priority":"warning","delivery":"inbox","trigger":{"kind":"eventCountAtLeast","eventType":"button.falsePositive","count":1},"body":["Panel zaznamenal odchylku mezi provedeným úkonem a očekáváním, které nebylo předem sděleno.","Událost lze po zakoupení review postupu převést na další schvalovací materiál."]},
  {"id":"memo.button-certified","from":"Komise pro Opakovaný Souhlas","subject":"Certifikace potvrzovací sekvence","priority":"high","delivery":"modal-once","trigger":{"kind":"moduleCertified","moduleId":"button-compliance"},"body":["Byla potvrzena schopnost potvrzovat v prostředí s dostatečným množstvím potvrzení.","Kompetence zůstává evidována i v případě, že se obsah souhlasu později změní."]},
  {"id":"memo.source-attribution","from":"Analytika Původu Interakcí","subject":"Kliky mají oddělení","priority":"normal","delivery":"inbox","trigger":{"kind":"upgradeOwned","upgradeId":"click.source-attribution"},"body":["Kliky provedené ve Fidgetu, Bloomu, formulářích a dalších modulech lze nyní zobrazit podle zdroje.","Zdroj interakce není totéž co její účel. Účel se nadále nesleduje."]},
  {"id":"memo.perceived-productivity-disclosed","from":"Nezávislá Jednotka Předpokládaného Výkonu","subject":"Perceived Productivity zpřístupněna","priority":"normal","delivery":"modal-once","trigger":{"kind":"upgradeOwned","upgradeId":"sys.resource-ledger"},"body":["Systém zpřístupnil metriku Perceived Productivity.","Metrika byla počítána od začátku relace. Skutečnost, že jste o ní nevěděli, neměla vliv na její přesvědčivost."]},
  {"id":"memo.departmental-routing","from":"Change Team / Dočasné Směrování","subject":"Mezioddělové vazby aktivní","priority":"high","delivery":"modal-once","trigger":{"kind":"upgradeOwned","upgradeId":"sys.departmental-routing"},"body":["Výsledky jednoho modulu mohou od této chvíle měnit podmínky jiného modulu.","Oddělení nebyla požádána o souhlas. Souhlas je řešen samostatným oddělením."]},
  {"id":"memo.wellbeing-audit","from":"Wellbeing Compliance","subject":"Wellbeing Audit zaveden","priority":"normal","delivery":"inbox","trigger":{"kind":"upgradeOwned","upgradeId":"cross.wellbeing-audit"},"body":["Nízká entropie byla uznána jako stav podporující vykazování.","Wellbeing benefit byl započítán. Odpočinek zůstává mimo rozsah."]},
  {"id":"memo.stabilized-confirmation","from":"Joint Stabilization & Consent Working Group","subject":"Stabilizovaný souhlas","priority":"normal","delivery":"inbox","trigger":{"kind":"upgradeOwned","upgradeId":"cross.stabilized-confirmation"},"body":["První potvrzovací sekvence po přirozeném doběhu nyní získává zvýšenou výkazní váhu.","Pohyb skončil. Jeho administrativní následky pokračují."]},
  {"id":"memo.passive-presence","from":"Oddělení Rohového Očekávání / Auditní Liaison","subject":"Pasivní přítomnost uznána","priority":"normal","delivery":"inbox","trigger":{"kind":"upgradeOwned","upgradeId":"cross.passive-presence"},"body":["Dokončené rohové pozorování lze nově použít jako doplňující auditní stopu.","K0rp_OS eviduje pouze události uvnitř modulu. Co jste během čekání dělali mimo něj, systém neví a nepotřebuje vědět."]},
  {"id":"memo.closure-eligible","from":"Komise pro Uzavírání Otevřeného","subject":"Auditní cyklus lze uzavřít","priority":"high","delivery":"modal-once","trigger":{"kind":"upgradeOwned","upgradeId":"sys.cycle-closure-authority"},"body":["Bylo shromážděno dostatečné množství výsledků, postupů a potvrzení k uzavření cyklu.","Uzavření odstraní dočasné procesní hodnoty, zachová certifikace a vytvoří Schválené Závěry."]},
  {"id":"memo.cycle-closed","from":"Office of Continuous Closure","subject":"Auditní cyklus uzavřen","priority":"ceremonial","delivery":"modal-once","trigger":{"kind":"eventCountAtLeast","eventType":"system.auditCycleClosed","count":1},"body":["Cyklus byl úspěšně uzavřen. Dočasná evidence byla archivována tak, aby mohla být znovu vytvořena efektivněji.","Na základě zjištění byl zpřístupněn nový wellbeing materiál: Bublinková Fólie.","Další cyklus může začít, jakmile bude přítomnost znovu řádně potvrzena."]}
]
